wimby_jobcreation/wimby_jobcreation_functions.py
wimby_jobcreation/data/jobcreation_review_data.csv
wimby_jobcreation-1.0.0.dist-info/licenses/LICENSE
wimby_jobcreation-1.0.0.dist-info/METADATA
wimby_jobcreation-1.0.0.dist-info/WHEEL
wimby_jobcreation-1.0.0.dist-info/top_level.txt
wimby_jobcreation-1.0.0.dist-info/RECORD
