Metadata-Version: 2.4
Name: wimby_jobcreation
Version: 1.0.0
Summary: A package for the WIMBY job creation functions
Author: Andrei del Villar, Sam Klap
Author-email: Luis Ramirez Camargo <l.e.ramirezcamargo@uu.nl>
Maintainer-email: Luis Ramirez Camargo <l.e.ramirezcamargo@uu.nl>
License: MIT License
Classifier: Development Status :: 4 - Beta
Classifier: Programming Language :: Python
Requires-Python: >=3.8
License-File: LICENSE
Requires-Dist: pandas
Dynamic: license-file
